LICENSE.txt
MANIFEST.in
README.md
pyproject.toml
setup.cfg
src/accurate_timed_loop/__init__.py
src/accurate_timed_loop/build_info.py
src/accurate_timed_loop/constants_version.py
src/accurate_timed_loop/main.py
src/accurate_timed_loop.egg-info/PKG-INFO
src/accurate_timed_loop.egg-info/SOURCES.txt
src/accurate_timed_loop.egg-info/dependency_links.txt
src/accurate_timed_loop.egg-info/requires.txt
src/accurate_timed_loop.egg-info/top_level.txt