Metadata-Version: 2.4
Name: accurate-timed-loop
Version: 1.0.0
Summary: accurate timed loop
Author-email: "J. Arrizza" <cppgent0@gmail.com>
Maintainer-email: "J. Arrizza" <cppgent0@gmail.com>
License-Expression: MIT
Project-URL: Website, https://arrizza.com/python-accurate-timed-loop
Project-URL: Source, https://bitbucket.org/arrizza-public/accurate-timed-loop/src/master
Project-URL: Download, https://bitbucket.org/arrizza-public/accurate-timed-loop/get/master.zip
Keywords: accurate loop,utility
Classifier: Development Status :: 5 - Production/Stable
Classifier: Environment :: Console
Classifier: Topic :: Utilities
Classifier: Intended Audience :: Developers
Classifier: Programming Language :: Python :: 3.10
Classifier: Programming Language :: Python :: 3.12
Requires-Python: >=3.9
License-File: LICENSE.txt
Requires-Dist: falcon-logger
Dynamic: license-file
